agentique/__init__.py
agentique/py.typed
agentique-0.1.2.dist-info/WHEEL
agentique-0.1.2.dist-info/METADATA
agentique-0.1.2.dist-info/RECORD
