Metadata-Version: 2.3
Name: agentique
Version: 0.1.2
Summary: Bridge the Model Context Protocol with the Agent2Agent protocol.
Requires-Dist: fastmcp>=3.0.0b1
Requires-Python: >=3.12
